bs_table_py/__init__.py
bs_table_py/lazy_join.py
bs_table_py/table.py
bootstrap_table_py-1.0.1.dist-info/LICENSE
bootstrap_table_py-1.0.1.dist-info/METADATA
bootstrap_table_py-1.0.1.dist-info/WHEEL
bootstrap_table_py-1.0.1.dist-info/top_level.txt
bootstrap_table_py-1.0.1.dist-info/RECORD
