Metadata-Version: 1.2
Name: bootstrap-table-py
Version: 1.0.1
Summary: Python wrapper for bootstrap-table
Home-page: https://github.com/agdsn/bootstrap-table-py/
Author: The Pycroft Authors
License: Apache Software License
Platform: UNKNOWN
Classifier: Development Status :: 5 - Production/Stable
Classifier: Environment :: Web Environment
Classifier: Intended Audience :: System Administrators
Classifier: License :: OSI Approved :: Apache Software License
Classifier: Operating System :: OS Independent
Classifier: Programming Language :: Python :: 3.5
Classifier: Programming Language :: Python :: 3.6
Classifier: Programming Language :: Python :: 3.7
Requires-Python: >= 3.5
